exceptiongroup/__init__.py
exceptiongroup/_catch.py
exceptiongroup/_exceptions.py
exceptiongroup/_formatting.py
exceptiongroup/_version.py
exceptiongroup/py.typed
exceptiongroup-1.0.0rc6.dist-info/LICENSE
exceptiongroup-1.0.0rc6.dist-info/WHEEL
exceptiongroup-1.0.0rc6.dist-info/METADATA
exceptiongroup-1.0.0rc6.dist-info/RECORD
