Metadata-Version: 2.1
Name: exceptiongroup
Version: 1.0.0rc6
Summary: Backport of PEP 654 (exception groups)
Author-email: Alex Grönholm <alex.gronholm@nextday.fi>
Requires-Python: >=3.7
Classifier: Development Status :: 5 - Production/Stable
Classifier: Intended Audience :: Developers
Classifier: License :: OSI Approved :: MIT License
Classifier: Programming Language :: Python
Classifier: Programming Language :: Python :: 3 :: Only
Classifier: Typing :: Typed
Requires-Dist: pytest >= 6 ; extra == "test"
Project-URL: Changelog, https://github.com/agronholm/exceptiongroup/blob/main/CHANGES.rst
Project-URL: Issue Tracker, https://github.com/agronholm/exceptiongroup/issues
Project-URL: Source code, https://github.com/agronholm/exceptiongroup
Provides-Extra: test
